LICENSE
README.md
pyproject.toml
reqif/__init__.py
reqif/object_lookup.py
reqif/parser.py
reqif/reqif_bundle.py
reqif/specification_iterator.py
reqif/unparser.py
reqif/cli/__init__.py
reqif/cli/cli_arg_parser.py
reqif/cli/main.py
reqif/commands/__init__.py
reqif/commands/anonymize/__init__.py
reqif/commands/anonymize/anonymize.py
reqif/commands/dump/__init__.py
reqif/commands/dump/dump.py
reqif/commands/dump/templates/index.jinja.html
reqif/commands/format/__init__.py
reqif/commands/format/format.py
reqif/commands/passthrough/__init__.py
reqif/commands/passthrough/passthrough.py
reqif/commands/validate/__init__.py
reqif/commands/validate/validate.py
reqif/commands/version/__init__.py
reqif/commands/version/version_command.py
reqif/experimental/reqif_schema.py
reqif/helpers/__init__.py
reqif/helpers/debug.py
reqif/helpers/lxml.py
reqif/helpers/reqif_datetime.py
reqif/helpers/string/__init__.py
reqif/helpers/string/escape.py
reqif/helpers/string/xhtml_indent.py
reqif/models/__init__.py
reqif/models/error_handling.py
reqif/models/reqif_core_content.py
reqif/models/reqif_data_type.py
reqif/models/reqif_namespace_info.py
reqif/models/reqif_relation_group.py
reqif/models/reqif_relation_group_type.py
reqif/models/reqif_req_if_content.py
reqif/models/reqif_reqif_header.py
reqif/models/reqif_spec_hierarchy.py
reqif/models/reqif_spec_object.py
reqif/models/reqif_spec_object_type.py
reqif/models/reqif_spec_relation.py
reqif/models/reqif_spec_relation_type.py
reqif/models/reqif_specification.py
reqif/models/reqif_specification_type.py
reqif/models/reqif_types.py
reqif/parsers/__init__.py
reqif/parsers/attribute_definition_parser.py
reqif/parsers/attribute_value_parser.py
reqif/parsers/data_type_parser.py
reqif/parsers/header_parser.py
reqif/parsers/relation_group_parser.py
reqif/parsers/spec_hierarchy_parser.py
reqif/parsers/spec_object_parser.py
reqif/parsers/spec_relation_parser.py
reqif/parsers/specification_parser.py
reqif/parsers/spec_types/relation_group_type_parser.py
reqif-0.0.48.dist-info/METADATA
reqif-0.0.48.dist-info/WHEEL
reqif-0.0.48.dist-info/entry_points.txt
reqif-0.0.48.dist-info/licenses/LICENSE
reqif-0.0.48.dist-info/RECORD
