Metadata-Version: 2.4
Name: reqif
Version: 0.0.48
Summary: Python library for ReqIF format. ReqIF parsing and unparsing.
Project-URL: Changelog, https://github.com/strictdoc-project/reqif/releases
Project-URL: Homepage, https://github.com/strictdoc-project/reqif
Project-URL: Source, https://github.com/strictdoc-project/reqif
Author-email: Stanislav Pankevich <s.pankevich@gmail.com>
License: Apache-2.0
License-File: LICENSE
Classifier: License :: OSI Approved :: Apache Software License
Classifier: Operating System :: OS Independent
Classifier: Programming Language :: Python :: 3
Classifier: Programming Language :: Python :: 3.8
Classifier: Programming Language :: Python :: 3.9
Classifier: Programming Language :: Python :: 3.10
Classifier: Programming Language :: Python :: 3.11
Classifier: Programming Language :: Python :: 3.12
Classifier: Programming Language :: Python :: 3.13
Classifier: Programming Language :: Python :: Implementation :: CPython
Classifier: Programming Language :: Python :: Implementation :: PyPy
Requires-Python: >=3.8
Requires-Dist: jinja2>=2.11.2
Requires-Dist: lxml>=4.6.2
Requires-Dist: openpyxl
Requires-Dist: xmlschema>=2.4.0
Provides-Extra: development
Requires-Dist: black>=21.9b0; extra == 'development'
Requires-Dist: coverage>=5.4; extra == 'development'
Requires-Dist: dataclasses-json; extra == 'development'
Requires-Dist: filecheck>=0.0.20; extra == 'development'
Requires-Dist: flake8>=3.9.2; extra == 'development'
Requires-Dist: html5lib>=1.1; extra == 'development'
Requires-Dist: invoke>=1.4.1; extra == 'development'
Requires-Dist: lit>=0.11.0.post1; extra == 'development'
Requires-Dist: mypy==1.16; extra == 'development'
Requires-Dist: pylint>=2.11.1; extra == 'development'
Requires-Dist: pytest>=6.2.2; extra == 'development'
Requires-Dist: pytidylib>=0.3.2; extra == 'development'
Requires-Dist: ruff>=0.0.243; extra == 'development'
